codegpt/__init__.py
codegpt/agent.py
codegpt_sdk-1.0.3.dist-info/LICENSE
codegpt_sdk-1.0.3.dist-info/METADATA
codegpt_sdk-1.0.3.dist-info/WHEEL
codegpt_sdk-1.0.3.dist-info/top_level.txt
codegpt_sdk-1.0.3.dist-info/RECORD
