Metadata-Version: 2.1
Name: codegpt-sdk
Version: 1.0.3
Summary: CODEGPT python package
Home-page: https://github.com/JudiniLabs/codegpt-python-sdk
Author: Daniel Avila
Author-email: daniel@judini.ai
Classifier: Programming Language :: Python :: 3
Classifier: License :: OSI Approved :: MIT License
Classifier: Operating System :: OS Independent
Requires-Python: >=3.6
License-File: LICENSE
